xint_sdk/__init__.py
xint_sdk/interactsh.py
xint_sdk/py.typed
xint_sdk-0.0.6.dist-info/METADATA
xint_sdk-0.0.6.dist-info/WHEEL
xint_sdk-0.0.6.dist-info/licenses/LICENSE
xint_sdk-0.0.6.dist-info/RECORD
