Metadata-Version: 2.4
Name: xint-sdk
Version: 0.0.6
Summary: Xint SDK
Project-URL: Homepage, https://xint.io
Project-URL: Issues, https://xint.io
Author-email: Xint Team <contact@xint.io>
License: Copyright 2025 Theori
License-File: LICENSE
Classifier: License :: OSI Approved :: MIT License
Classifier: Operating System :: OS Independent
Classifier: Programming Language :: Python :: 3
Classifier: Programming Language :: Python :: 3 :: Only
Classifier: Programming Language :: Python :: 3.9
Classifier: Programming Language :: Python :: 3.10
Classifier: Programming Language :: Python :: 3.11
Classifier: Programming Language :: Python :: 3.12
Classifier: Programming Language :: Python :: 3.13
Requires-Python: >=3.9
Requires-Dist: pycryptodomex==3.23.0
Requires-Dist: requests==2.32.5
Provides-Extra: dev
Requires-Dist: pyright<2.0.0,>=1.1.400; extra == 'dev'
Requires-Dist: pytest<9.0.0,>=8.3.4; extra == 'dev'
Requires-Dist: ruff<1.0.0,>=0.9.2; extra == 'dev'
